Metadata-Version: 2.1
Name: hello-from-world
Version: 1.12.0
Summary: Just a random package
License: MIT
License-File: LICENSE
